dataframe_packing/__init__.py
dataframe_packing/tests/__init__.py
dataframe_packing/tests/test_all.py
DataframePacking-22.6.7.1.dist-info/METADATA
DataframePacking-22.6.7.1.dist-info/WHEEL
DataframePacking-22.6.7.1.dist-info/top_level.txt
DataframePacking-22.6.7.1.dist-info/RECORD
