Metadata-Version: 2.1
Name: DataframePacking
Version: 22.6.7.1
Requires-Dist: pandas (>=0.24.1)
